shuffleboard2js/__init__.py
shuffleboard2js/__main__.py
shuffleboard2js/version.py
shuffleboard2js/html/dist/3-axis-accelerometer.bundle.js
shuffleboard2js/html/dist/3cf97837524dd7445e9d1462e3c4afe2.woff
shuffleboard2js/html/dist/47151e87c5a8666791a91007de4962da.eot
shuffleboard2js/html/dist/527eff645d8ead16666afb6931041279.otf
shuffleboard2js/html/dist/93cc7aa654ae36b0828716f5ec3159cd.ttf
shuffleboard2js/html/dist/accelerometer.bundle.js
shuffleboard2js/html/dist/app.bundle.js
shuffleboard2js/html/dist/basic-fms-info.bundle.js
shuffleboard2js/html/dist/basic-subsystem.bundle.js
shuffleboard2js/html/dist/boolean-box.bundle.js
shuffleboard2js/html/dist/camera.bundle.js
shuffleboard2js/html/dist/combobox-chooser.bundle.js
shuffleboard2js/html/dist/differential-drivebase.bundle.js
shuffleboard2js/html/dist/encoder.bundle.js
shuffleboard2js/html/dist/gauge.bundle.js
shuffleboard2js/html/dist/gyro.bundle.js
shuffleboard2js/html/dist/index.html
shuffleboard2js/html/dist/mecanum-drivebase.bundle.js
shuffleboard2js/html/dist/number-bar.bundle.js
shuffleboard2js/html/dist/number-slider.bundle.js
shuffleboard2js/html/dist/relay.bundle.js
shuffleboard2js/html/dist/text-view.bundle.js
shuffleboard2js/html/dist/toggle-button.bundle.js
shuffleboard2js/html/dist/toggle-switch.bundle.js
shuffleboard2js/html/dist/voltage-view.bundle.js
shuffleboard2js/html/dist/assets/media/3-axis-accelerometer.png
shuffleboard2js/html/dist/assets/media/accelerometer.png
shuffleboard2js/html/dist/assets/media/basic-fms-info.png
shuffleboard2js/html/dist/assets/media/basic-subsystem.png
shuffleboard2js/html/dist/assets/media/boolean-box.png
shuffleboard2js/html/dist/assets/media/camera.png
shuffleboard2js/html/dist/assets/media/combobox-chooser.png
shuffleboard2js/html/dist/assets/media/differential-drivebase.png
shuffleboard2js/html/dist/assets/media/encoder.png
shuffleboard2js/html/dist/assets/media/file-8x.png
shuffleboard2js/html/dist/assets/media/gauge.png
shuffleboard2js-2019.0.2.dist-info/METADATA
shuffleboard2js-2019.0.2.dist-info/WHEEL
shuffleboard2js-2019.0.2.dist-info/entry_points.txt
shuffleboard2js-2019.0.2.dist-info/top_level.txt
shuffleboard2js-2019.0.2.dist-info/RECORD
