Metadata-Version: 2.1
Name: shuffleboard2js
Version: 2019.0.2
Summary: Web based HTML dashboard for FRC
Home-page: https://github.com/robotpy/shuffleboard2js
Author: Amory Galili
Author-email: robotpy@googlegroups.com
License: BSD License
Platform: UNKNOWN
Classifier: Development Status :: 4 - Beta
Classifier: Intended Audience :: Developers
Classifier: Intended Audience :: Education
Classifier: License :: OSI Approved :: BSD License
Classifier: Operating System :: OS Independent
Classifier: Programming Language :: Python :: 3.4
Classifier: Topic :: Scientific/Engineering
Requires-Dist: tornado (>=5.0.2)
Requires-Dist: pynetworktables (>=2019.0.0)
Requires-Dist: pynetworktables2js (>=2019.0.0)
